nlit/__init__.py
nlit/_modidx.py
nlit/args.py
nlit/attr.py
nlit/biol.py
nlit/bkts.py
nlit/byte.py
nlit/cell.py
nlit/clrs.py
nlit/dict.py
nlit/docs.py
nlit/dund.py
nlit/embs.py
nlit/errs.py
nlit/expo.py
nlit/exps.py
nlit/exts.py
nlit/fmtx.py
nlit/hrdw.py
nlit/math.py
nlit/mods.py
nlit/mthd.py
nlit/narr.py
nlit/nbks.py
nlit/ncls.py
nlit/path.py
nlit/pddf.py
nlit/pkgs.py
nlit/plot.py
nlit/sund.py
nlit/tens.py
nlit/text.py
nlit/tree.py
nlit/unit.py
nlit/vals.py
nlit/vers.py
nlit-0.0.97.dist-info/LICENSE
nlit-0.0.97.dist-info/METADATA
nlit-0.0.97.dist-info/WHEEL
nlit-0.0.97.dist-info/entry_points.txt
nlit-0.0.97.dist-info/top_level.txt
nlit-0.0.97.dist-info/RECORD
