Metadata-Version: 2.1
Name: nlit
Version: 0.0.97
Summary: nlit
Home-page: https://github.com/dsm-72/nlit
Author: dsm-72
Author-email: sumner.magruder@yale.edu
License: Apache Software License 2.0
Keywords: nlit named string literal str literals
Classifier: Development Status :: 4 - Beta
Classifier: Intended Audience :: Developers
Classifier: Natural Language :: English
Classifier: Programming Language :: Python :: 3.11
Classifier: License :: OSI Approved :: Apache Software License
Requires-Python: >=3.11
License-File: LICENSE
Requires-Dist: nchr
Provides-Extra: dev
Requires-Dist: ipython ; extra == 'dev'
